akkadian/__init__.py
akkadian/bilstm.py
akkadian/build_data.py
akkadian/check_translation.py
akkadian/combine_algorithms.py
akkadian/data.py
akkadian/full_translation_build_data.py
akkadian/get_texts_details.py
akkadian/hmm.py
akkadian/memm.py
akkadian/parse_json.py
akkadian/parse_xml.py
akkadian/train.py
akkadian/translate_common.py
akkadian/translate_cuneiform.py
akkadian/translate_from_cuneiform.py
akkadian/translate_from_transliteration.py
akkadian/translate_transliteration.py
akkadian/translation_memory.py
akkadian/translation_tokenize.py
akkadian/transliterate.py
akkadian/output/bilstm_model_linux.pkl
akkadian/output/bilstm_model_windows.pkl
akkadian/output/hmm_model.pkl
akkadian/output/memm_model.pkl
akkadian-1.0.12.dist-info/LICENSE
akkadian-1.0.12.dist-info/METADATA
akkadian-1.0.12.dist-info/WHEEL
akkadian-1.0.12.dist-info/top_level.txt
akkadian-1.0.12.dist-info/RECORD
