Metadata-Version: 2.1
Name: akkadian
Version: 1.0.12
Summary: Translating Akkadian signs to transliteration using NLP algorithms
Home-page: https://github.com/gaigutherz/Akkademia
Author: Gai Gutherz, Ariel Elazary
Author-email: gaigutherz@gmail.com, am.elazary@gmail.com
Classifier: Programming Language :: Python :: 3.7
Classifier: License :: OSI Approved :: MIT License
Classifier: Operating System :: OS Independent
License-File: LICENSE
Requires-Dist: allennlp (==0.8.5)
